scalarpy/__init__.py
scalarpy/pre_process.py
scalarpy/scalarpy_classifier.py
scalarpy/scalarpy_regressor.py
scalarpy-0.0.1b6.dist-info/LICENSE
scalarpy-0.0.1b6.dist-info/METADATA
scalarpy-0.0.1b6.dist-info/WHEEL
scalarpy-0.0.1b6.dist-info/top_level.txt
scalarpy-0.0.1b6.dist-info/RECORD
