Metadata-Version: 2.1
Name: scalarpy
Version: 0.0.1b6
Summary: Welcome to ScalarPy!
Home-page: https://github.com/ScalarPy/scalarpy
Author: G D Abhishek
Author-email: gdabhishek1@gmail.com
License: UNKNOWN
Platform: UNKNOWN
Classifier: Programming Language :: Python :: 3
Classifier: License :: OSI Approved :: MIT License
Classifier: Operating System :: OS Independent
Requires-Python: >=3.1
Requires-Dist: pandas
Requires-Dist: numpy
Requires-Dist: matplotlib
Requires-Dist: scipy
Requires-Dist: scikit-learn
Requires-Dist: imblearn
Requires-Dist: xgboost
Requires-Dist: lightgbm
Requires-Dist: ipywidgets
Requires-Dist: yellowbrick
